{
  "data": {
    "contractId": "16LC0034",
    "description": "DEEPENING/ WIDENING OF TUGANAY RIVER (DOWNSTREAM OF TUGANAY BRIDGE) CARMEN, DAVAO DEL NORTE, STA. 7+058-STA. 8+335 (STA. 7+033-STA.6+335)",
    "category": "Flood Control and Drainage",
    "status": "Completed",
    "budget": 21230000,
    "amountPaid": 0,
    "progress": 100,
    "location": {
      "region": "Region XI",
      "province": "Davao del Norte DEO",
      "infraType": "Flood Control and Drainage",
      "coordinates": null
    },
    "infraType": "Flood Control and Drainage",
    "contractor": "LEGACY CONSTRUCTION CORPORATION (FORMERLY: LEGACY CONSTRUCTION) (22465)",
    "startDate": "2016-08-04",
    "completionDate": "2016-11-10",
    "infraYear": "2016",
    "contractEffectivityDate": "2016-08-04",
    "expiryDate": "2016-11-11",
    "nysReason": null,
    "programName": "Regular Infra",
    "sourceOfFunds": "Regular Infra - GAA 2016 MFO-2",
    "isVerifiedByDpwh": false,
    "isVerifiedByPublic": false,
    "isLive": false,
    "livestreamUrl": null,
    "livestreamVideoId": null,
    "livestreamDetectedAt": null,
    "components": [
      {
        "componentId": "P00022775MN-CW1",
        "description": "Construction of Waterway - Deepening/Widening of Tuganay River (Downstream of Tuganay Bridge), Carmen, Davao del Norte (Sta. 7+058 - Sta. 8+335)",
        "infraType": "Flood Control and Drainage",
        "typeOfWork": "Construction of Waterway",
        "region": "Region XI",
        "province": "DAVAO DEL NORTE",
        "coordinates": null
      }
    ],
    "winnerNames": "LEGACY CONSTRUCTION CORPORATION (FORMERLY: LEGACY CONSTRUCTION)",
    "bidders": [
      {
        "name": "LEGACY CONSTRUCTION CORPORATION (FORMERLY: LEGACY CONSTRUCTION) (22465)",
        "pcabId": "22465",
        "participation": 100,
        "isWinner": true
      },
      {
        "name": "DIGOS TESSTON CONST. & SUPPLIES (8921)",
        "pcabId": "8921",
        "participation": 100,
        "isWinner": false
      },
      {
        "name": "FFJJ CONSTRUCTION (16712)",
        "pcabId": "16712",
        "participation": 100,
        "isWinner": false
      }
    ],
    "procurement": {
      "contractName": "DEEPENING/ WIDENING OF TUGANAY RIVER (DOWNSTREAM OF TUGANAY BRIDGE) CARMEN, DAVAO DEL NORTE, STA. 7+058-STA. 8+335 (STA. 7+033-STA.6+335)",
      "abc": "21230000.00",
      "status": "A",
      "fundingInstrument": "GOP-GOVERNMENT OF THE PHILIPPINES",
      "advertisementDate": "2016-02-19 00:00:00.0000000",
      "bidSubmissionDeadline": "2016-07-07 00:00:00.0000000",
      "dateOfAward": null,
      "awardAmount": "21,105,134.81"
    },
    "links": {
      "advertisement": "",
      "contractAgreement": "https://archive.dpwh.gov.ph/post/cw/pdf/cw/contract/16/august/Approved Contract Agreement 15LC0034.pdf",
      "noticeOfAward": "https://archive.dpwh.gov.ph/post/cw/pdf/cw/noa/16/july/Approved NOA 16LC0034.pdf",
      "noticeToProceed": "https://archive.dpwh.gov.ph/post/cw/pdf/cw/contract/16/august/Approved Contract Agreement 15LC0034.pdf",
      "programOfWork": "",
      "engineeringDesign": ""
    },
    "latitude": null,
    "longitude": null,
    "coordinates": [],
    "imageSummary": {
      "totalImages": 0,
      "latestImageDate": null,
      "hasImages": false
    }
  }
}