{
  "data": {
    "contractId": "25GD0045",
    "description": "WIDENING OF BRIDGE - ADLAWAN BR. (B00494PN) ALONG LANOT-LOCTUGAN-PANITAN BDRY RD.",
    "category": "Bridges",
    "status": "On-Going",
    "budget": 7784727.61,
    "amountPaid": 0,
    "progress": 0,
    "location": {
      "region": "Region VI",
      "province": "Capiz 1st DEO",
      "infraType": "Bridges",
      "coordinates": null
    },
    "infraType": "Bridges",
    "contractor": "JGC CONSTRUCTION (49373)",
    "startDate": "2025-07-08",
    "completionDate": null,
    "infraYear": "2025",
    "contractEffectivityDate": "2025-07-08",
    "expiryDate": "2026-01-10",
    "nysReason": null,
    "programName": "Regular Infra",
    "sourceOfFunds": "Regular Infra - GAA 2025 OO-1",
    "isVerifiedByDpwh": false,
    "isVerifiedByPublic": false,
    "isLive": false,
    "livestreamUrl": null,
    "livestreamVideoId": null,
    "livestreamDetectedAt": null,
    "components": [
      {
        "componentId": "P00906866VS-CW1",
        "description": "Widening of Bridge - Adlawan Br. (B00494PN) along Lanot-Loctugan-Panitan Bdry Rd",
        "infraType": "Bridges",
        "typeOfWork": "Widening of Bridge",
        "region": "Region VI",
        "province": "CAPIZ",
        "coordinates": null
      },
      {
        "componentId": "P00906866VS-CW2",
        "description": "Construction of Bridge Approach - Adlawan Br. (B00494PN) along Lanot-Loctugan-Panitan Bdry Rd",
        "infraType": "Bridges",
        "typeOfWork": "Construction of Bridge Approach",
        "region": "Region VI",
        "province": "CAPIZ",
        "coordinates": null
      }
    ],
    "winnerNames": "JGC CONSTRUCTION",
    "bidders": [
      {
        "name": "JGC CONSTRUCTION (49373)",
        "pcabId": "49373",
        "participation": 100,
        "isWinner": true
      },
      {
        "name": "EDLY CONSTRUCTION AND DEVELOPMENT CORPORATION (34421)",
        "pcabId": "34421",
        "participation": 100,
        "isWinner": false
      }
    ],
    "procurement": {
      "contractName": "WIDENING OF BRIDGE - ADLAWAN BR. (B00494PN) ALONG LANOT-LOCTUGAN-PANITAN BDRY RD.",
      "abc": "7840000.00",
      "status": "A",
      "fundingInstrument": "GOP-GOVERNMENT OF THE PHILIPPINES",
      "advertisementDate": "2025-03-04 00:00:00.0000000",
      "bidSubmissionDeadline": "2025-03-25 00:00:00.0000000",
      "dateOfAward": "2025-06-17 00:00:00.0000000",
      "awardAmount": "7784727.61"
    },
    "links": {
      "advertisement": "https://www.dpwh.gov.ph/dpwh/sites/default/files/webform/civil_works/advertisement/bidding_documents_25gd0045.zip",
      "contractAgreement": "https://www.dpwh.gov.ph/dpwh/sites/default/files/webform/civil_works/contract_of_agreement/25gd0045-contract.pdf",
      "noticeOfAward": "https://www.dpwh.gov.ph/dpwh/sites/default/files/webform/civil_works/notice_of_award/25gd0045-noa_reso.zip",
      "noticeToProceed": "https://www.dpwh.gov.ph/dpwh/sites/default/files/webform/civil_works/notice_to_proceed/25gd0045-ntp.pdf",
      "programOfWork": "",
      "engineeringDesign": ""
    },
    "latitude": null,
    "longitude": null,
    "coordinates": [],
    "imageSummary": {
      "totalImages": 0,
      "latestImageDate": null,
      "hasImages": false
    }
  }
}